setup.cfg
setup.py
log_run_source/__init__.py
log_run_source.egg-info/PKG-INFO
log_run_source.egg-info/SOURCES.txt
log_run_source.egg-info/dependency_links.txt
log_run_source.egg-info/top_level.txt