Metadata-Version: 1.1
Name: log-run-source
Version: 0.0.3
Summary: A decorator that logs each line
Home-page: https://github.com/alehander42/python-log-run-source
Author: Alexander Ivanov
Author-email: alehander42@gmail.com
License: MIT
Download-URL: https://github.com/alehander42/python-log-run-source/archive/v0.0.1.tar.gz
Keywords: log,run
Platform: UNKNOWN
Classifier: Development Status :: 4 - Beta
Classifier: Programming Language :: Python
Classifier: Programming Language :: Python :: 3.3
Classifier: Programming Language :: Python :: 3.4
Classifier: Programming Language :: Python :: 3.5
Classifier: Programming Language :: Python :: 2.7
Classifier: Intended Audience :: Developers
Classifier: License :: OSI Approved :: MIT License
